classprop/__init__.py
classprop/classprop.py
classprop-0.1.1.dist-info/AUTHORS.rst
classprop-0.1.1.dist-info/LICENSE
classprop-0.1.1.dist-info/METADATA
classprop-0.1.1.dist-info/WHEEL
classprop-0.1.1.dist-info/top_level.txt
classprop-0.1.1.dist-info/RECORD
